{
  "n_rows": 57,
  "results": [
    {
      "row": 0,
      "prediction": "No Default",
      "probability": 0.2789,
      "risk_level": "Low"
    },
    {
      "row": 1,
      "prediction": "No Default",
      "probability": 0.2162,
      "risk_level": "Low"
    },
    {
      "row": 2,
      "prediction": "No Default",
      "probability": 0.1148,
      "risk_level": "Low"
    },
    {
      "row": 3,
      "prediction": "No Default",
      "probability": 0.2367,
      "risk_level": "Low"
    },
    {
      "row": 4,
      "prediction": "No Default",
      "probability": 0.2001,
      "risk_level": "Low"
    },
    {
      "row": 5,
      "prediction": "No Default",
      "probability": 0.1088,
      "risk_level": "Low"
    },
    {
      "row": 6,
      "prediction": "No Default",
      "probability": 0.2602,
      "risk_level": "Low"
    },
    {
      "row": 7,
      "prediction": "No Default",
      "probability": 0.2123,
      "risk_level": "Low"
    },
    {
      "row": 8,
      "prediction": "No Default",
      "probability": 0.4813,
      "risk_level": "Low"
    },
    {
      "row": 9,
      "prediction": "No Default",
      "probability": 0.2642,
      "risk_level": "Low"
    },
    {
      "row": 10,
      "prediction": "No Default",
      "probability": 0.0661,
      "risk_level": "Low"
    },
    {
      "row": 11,
      "prediction": "No Default",
      "probability": 0.0978,
      "risk_level": "Low"
    },
    {
      "row": 12,
      "prediction": "No Default",
      "probability": 0.2344,
      "risk_level": "Low"
    },
    {
      "row": 13,
      "prediction": "No Default",
      "probability": 0.2,
      "risk_level": "Low"
    },
    {
      "row": 14,
      "prediction": "No Default",
      "probability": 0.0088,
      "risk_level": "Low"
    },
    {
      "row": 15,
      "prediction": "No Default",
      "probability": 0.2928,
      "risk_level": "Low"
    },
    {
      "row": 16,
      "prediction": "No Default",
      "probability": 0.1144,
      "risk_level": "Low"
    },
    {
      "row": 17,
      "prediction": "No Default",
      "probability": 0.2214,
      "risk_level": "Low"
    },
    {
      "row": 18,
      "prediction": "No Default",
      "probability": 0.192,
      "risk_level": "Low"
    },
    {
      "row": 19,
      "prediction": "No Default",
      "probability": 0.2573,
      "risk_level": "Low"
    },
    {
      "row": 20,
      "prediction": "No Default",
      "probability": 0.2282,
      "risk_level": "Low"
    },
    {
      "row": 21,
      "prediction": "Default",
      "probability": 0.7288,
      "risk_level": "Medium"
    },
    {
      "row": 22,
      "prediction": "No Default",
      "probability": 0.0543,
      "risk_level": "Low"
    },
    {
      "row": 23,
      "prediction": "No Default",
      "probability": 0.2195,
      "risk_level": "Low"
    },
    {
      "row": 24,
      "prediction": "No Default",
      "probability": 0.1233,
      "risk_level": "Low"
    },
    {
      "row": 25,
      "prediction": "No Default",
      "probability": 0.3111,
      "risk_level": "Low"
    },
    {
      "row": 26,
      "prediction": "No Default",
      "probability": 0.1084,
      "risk_level": "Low"
    },
    {
      "row": 27,
      "prediction": "No Default",
      "probability": 0.0721,
      "risk_level": "Low"
    },
    {
      "row": 28,
      "prediction": "No Default",
      "probability": 0.1145,
      "risk_level": "Low"
    },
    {
      "row": 29,
      "prediction": "No Default",
      "probability": 0.0478,
      "risk_level": "Low"
    },
    {
      "row": 30,
      "prediction": "No Default",
      "probability": 0.4026,
      "risk_level": "Low"
    },
    {
      "row": 31,
      "prediction": "No Default",
      "probability": 0.2512,
      "risk_level": "Low"
    },
    {
      "row": 32,
      "prediction": "No Default",
      "probability": 0.0597,
      "risk_level": "Low"
    },
    {
      "row": 33,
      "prediction": "No Default",
      "probability": 0.2074,
      "risk_level": "Low"
    },
    {
      "row": 34,
      "prediction": "No Default",
      "probability": 0.1485,
      "risk_level": "Low"
    },
    {
      "row": 35,
      "prediction": "No Default",
      "probability": 0.1086,
      "risk_level": "Low"
    },
    {
      "row": 36,
      "prediction": "No Default",
      "probability": 0.0812,
      "risk_level": "Low"
    },
    {
      "row": 37,
      "prediction": "No Default",
      "probability": 0.3224,
      "risk_level": "Low"
    },
    {
      "row": 38,
      "prediction": "No Default",
      "probability": 0.1549,
      "risk_level": "Low"
    },
    {
      "row": 39,
      "prediction": "No Default",
      "probability": 0.1834,
      "risk_level": "Low"
    },
    {
      "row": 40,
      "prediction": "No Default",
      "probability": 0.2332,
      "risk_level": "Low"
    },
    {
      "row": 41,
      "prediction": "No Default",
      "probability": 0.2176,
      "risk_level": "Low"
    },
    {
      "row": 42,
      "prediction": "No Default",
      "probability": 0.1256,
      "risk_level": "Low"
    },
    {
      "row": 43,
      "prediction": "No Default",
      "probability": 0.1882,
      "risk_level": "Low"
    },
    {
      "row": 44,
      "prediction": "No Default",
      "probability": 0.3234,
      "risk_level": "Low"
    },
    {
      "row": 45,
      "prediction": "No Default",
      "probability": 0.2222,
      "risk_level": "Low"
    },
    {
      "row": 46,
      "prediction": "Default",
      "probability": 0.7107,
      "risk_level": "Medium"
    },
    {
      "row": 47,
      "prediction": "No Default",
      "probability": 0.2075,
      "risk_level": "Low"
    },
    {
      "row": 48,
      "prediction": "Default",
      "probability": 0.5039,
      "risk_level": "Medium"
    },
    {
      "row": 49,
      "prediction": "No Default",
      "probability": 0.4338,
      "risk_level": "Low"
    },
    {
      "row": 50,
      "prediction": "No Default",
      "probability": 0.2278,
      "risk_level": "Low"
    },
    {
      "row": 51,
      "prediction": "No Default",
      "probability": 0.1932,
      "risk_level": "Low"
    },
    {
      "row": 52,
      "prediction": "No Default",
      "probability": 0.0642,
      "risk_level": "Low"
    },
    {
      "row": 53,
      "prediction": "No Default",
      "probability": 0.2168,
      "risk_level": "Low"
    },
    {
      "row": 54,
      "prediction": "No Default",
      "probability": 0.2454,
      "risk_level": "Low"
    },
    {
      "row": 55,
      "prediction": "No Default",
      "probability": 0.1233,
      "risk_level": "Low"
    },
    {
      "row": 56,
      "prediction": "No Default",
      "probability": 0.2165,
      "risk_level": "Low"
    }
  ],
  "drift": [
    {
      "column": "dataset",
      "score": 0.875
    },
    {
      "column": "age",
      "score": 0.23371009362458137
    },
    {
      "column": "bill_amt_aug",
      "score": 0.15297297061013115
    },
    {
      "column": "bill_amt_sep",
      "score": 0.15343706502680868
    },
    {
      "column": "credit_limit",
      "score": 0.31403434449489975
    },
    {
      "column": "pay_amt_aug",
      "score": 0.11849030297054779
    },
    {
      "column": "pay_amt_sep",
      "score": 0.12469609378058553
    },
    {
      "column": "pay_delay_aug",
      "score": 0.2553718164587327
    },
    {
      "column": "pay_delay_sep",
      "score": 0.07397843471719741
    }
  ]
}